setup.py
replkeepalive/__init__.py
replkeepalive.egg-info/PKG-INFO
replkeepalive.egg-info/SOURCES.txt
replkeepalive.egg-info/dependency_links.txt
replkeepalive.egg-info/top_level.txt