Metadata-Version: 1.0
Name: replkeepalive
Version: 0.1.1
Summary: Keep repls alive.
Home-page: UNKNOWN
Author: UNKNOWN
Author-email: UNKNOWN
License: UNKNOWN
Platform: UNKNOWN
